wortsalat/__init__.py
wortsalat/analyze_wortsalat.py
wortsalat/count.py
wortsalat/identify_tags.py
wortsalat/identify_words.py
wortsalat/lix.py
wortsalat/preprocess.py
wortsalat/wrapper.py
wortsalat-0.0.5.dist-info/LICENSE
wortsalat-0.0.5.dist-info/METADATA
wortsalat-0.0.5.dist-info/WHEEL
wortsalat-0.0.5.dist-info/top_level.txt
wortsalat-0.0.5.dist-info/zip-safe
wortsalat-0.0.5.dist-info/RECORD
