Metadata-Version: 2.1
Name: wortsalat
Version: 0.0.5
Summary: An NLP python library for analyzing the german language.
Author: Petra
License: Apache License
Project-URL: Repository, https://github.com/petra-viola/wortsalat
Keywords: nlp,german nlp
Requires-Python: >=3.8
License-File: LICENSE
Requires-Dist: HanTa
Requires-Dist: nltk
Requires-Dist: numpy
Requires-Dist: textstat
